pySTLtools.py
pySTLtools-0.0.1.dist-info/LICENSE.txt
pySTLtools-0.0.1.dist-info/METADATA
pySTLtools-0.0.1.dist-info/WHEEL
pySTLtools-0.0.1.dist-info/top_level.txt
pySTLtools-0.0.1.dist-info/RECORD
