Metadata-Version: 2.1
Name: pySTLtools
Version: 0.0.1
Summary: A Python package for mathematical tools like in STL of C++
Home-page: https://github.com/rkat7/pySTL
Author: Rohith Kattamuri
Author-email: skrishrkat7@gmail.com
License: MIT
Platform: UNKNOWN
Classifier: License :: OSI Approved :: MIT License
Classifier: Programming Language :: Python :: 3
Classifier: Programming Language :: Python :: 3.6
Classifier: Programming Language :: Python :: 3.7
Classifier: Operating System :: OS Independent
Provides-Extra: dev
Requires-Dist: pytest (>=3.7) ; extra == 'dev'
